raspi_tools/__init__.py
raspi_tools/default.py
raspi_tools/gpsmanager.py
raspi_tools-1.0.19.dist-info/METADATA
raspi_tools-1.0.19.dist-info/WHEEL
raspi_tools-1.0.19.dist-info/top_level.txt
raspi_tools-1.0.19.dist-info/RECORD
