Metadata-Version: 2.2
Name: raspi_tools
Version: 1.0.19
Summary: A Python library for Raspberry Pi tools including GPS and board LED utilities.
Author: Elijah M
Author-email: gichiam22@gmail.com
Classifier: Programming Language :: Python :: 3
Classifier: Operating System :: POSIX :: Linux
Classifier: Topic :: System :: Hardware :: Hardware Drivers
Requires-Dist: gps
Requires-Dist: tinydb
Requires-Dist: tqdm
Dynamic: author
Dynamic: author-email
Dynamic: classifier
Dynamic: description
Dynamic: description-content-type
Dynamic: requires-dist
Dynamic: summary
